graphql_requests/__init__.py
graphql_requests/errors.py
graphql_requests/request.py
graphql_requests/typedefs.py
graphql_requests/utils.py
graphql_requests/client/__init__.py
graphql_requests/client/async_client.py
graphql_requests/client/base.py
graphql_requests/client/sync_client.py
graphql_requests-0.3.0.dist-info/LICENSE
graphql_requests-0.3.0.dist-info/WHEEL
graphql_requests-0.3.0.dist-info/METADATA
graphql_requests-0.3.0.dist-info/RECORD
